jupyterdart/__init__.py
jupyterdart/__main__.py
jupyterdart/install_kernelspec.py
jupyterdart/kernel.py
jupyterdart-0.1.0.dist-info/METADATA
jupyterdart-0.1.0.dist-info/WHEEL
jupyterdart-0.1.0.dist-info/top_level.txt
jupyterdart-0.1.0.dist-info/RECORD
